fracspy/__init__.py
fracspy/version.py
fracspy/detection/__init__.py
fracspy/detection/matched_filtering.py
fracspy/detection/stacking.py
fracspy/location/__init__.py
fracspy/location/imaging.py
fracspy/location/location.py
fracspy/location/migration.py
fracspy/location/utils.py
fracspy/modelling/__init__.py
fracspy/modelling/kirchhoff.py
fracspy/modelling/mt_kirchhoff.py
fracspy/modelling/trueamp_kirchhoff.py
fracspy/mtinversion/__init__.py
fracspy/mtinversion/greensfunction.py
fracspy/mtinversion/mtai.py
fracspy/mtinversion/mtinversion.py
fracspy/mtinversion/mtmodelling.py
fracspy/mtinversion/mtwi.py
fracspy/mtinversion/utils.py
fracspy/processing/__init__.py
fracspy/processing/filtering.py
fracspy/utils/__init__.py
fracspy/utils/sofiutils.py
fracspy/utils/synthutils.py
fracspy/visualisation/Plotting_Detected_Events.py
fracspy/visualisation/__init__.py
fracspy/visualisation/eventimages.py
fracspy/visualisation/momenttensor_plots.py
fracspy/visualisation/plotting_support.py
fracspy/visualisation/traceviz.py
fracspy-0.1.0.dist-info/LICENCE.md
fracspy-0.1.0.dist-info/METADATA
fracspy-0.1.0.dist-info/WHEEL
fracspy-0.1.0.dist-info/top_level.txt
fracspy-0.1.0.dist-info/RECORD
