Metadata-Version: 2.1
Name: fracspy
Version: 0.1.0
Summary: A python package for general microseismic modelling, monitoring and analysis
Author-email: Claire Emma Birnie <claire.birnie@kaust.edu.sa>, Denis Anikiev <denis.anikiev@gfz-potsdam.de>, Omar Sad Aly <omar.sadaly@kaust.edu.sa>, Matteo Ravasi <matteo.ravasi@kaust.edu.sa>
Keywords: geophysics,signal processing,microseismic
Classifier: Development Status :: 1 - Planning
Classifier: Intended Audience :: Developers
Classifier: Intended Audience :: Science/Research
Classifier: Intended Audience :: Education
Classifier: License :: OSI Approved :: MIT License
Classifier: Natural Language :: English
Classifier: Operating System :: OS Independent
Classifier: Programming Language :: Python :: 3 :: Only
Classifier: Programming Language :: Python :: 3.8
Classifier: Programming Language :: Python :: 3.9
Classifier: Programming Language :: Python :: 3.10
Classifier: Programming Language :: Python :: 3.11
License-File: LICENCE.md
Requires-Dist: numpy>=1.15.0
Requires-Dist: scipy>=1.8.0
Requires-Dist: matplotlib
Requires-Dist: pylops>=2.0.0
Requires-Dist: torch
Requires-Dist: cmcrameri
Requires-Dist: openpyxl
Requires-Dist: tqdm
Requires-Dist: obspy
Provides-Extra: test
Requires-Dist: pytest; extra == "test"
Requires-Dist: pytest-cov; extra == "test"
